modapp/__init__.py
modapp/watering/__app__.py
modapp/watering/__init__.py
modapp/watering/app.py
modapp/watering/autorestart.py
modapp/watering/boot_watering.py
modapp/watering/flow_meter.py
modapp/watering/program.py
modapp/watering/schedule.py
modapp/watering/scheduler.py
modapp/watering/settings.py
modapp/watering/state.py
modapp/watering/valves.py
modapp/watering/etc/flowmeter.template.json.txt
modapp/watering/etc/settings.template.json.txt
modapp/watering/etc/valves.template.json.txt
modapp/watering/www/index.html
mpymodcore_watering-0.0.13.dist-info/LICENSE
mpymodcore_watering-0.0.13.dist-info/METADATA
mpymodcore_watering-0.0.13.dist-info/WHEEL
mpymodcore_watering-0.0.13.dist-info/top_level.txt
mpymodcore_watering-0.0.13.dist-info/RECORD
