Metadata-Version: 2.1
Name: mpymodcore-watering
Version: 0.0.13
Summary: mpymodcore
Home-page: https://github.com/kr-g/mpymodcore_watering
Author: k. goger
Author-email: k.r.goger+mpymodcore_watering@gmail.com
License: https://github.com/kr-g/mpymodcore_watering/blob/master/LICENSE
Keywords: mpy-modcore micropython framework micro-framework esp32 esp8266
Classifier: Development Status :: 3 - Alpha
Classifier: Intended Audience :: Developers
Classifier: Intended Audience :: Information Technology
Classifier: Topic :: Software Development :: Embedded Systems
Classifier: Topic :: Utilities
Classifier: Topic :: Home Automation
Classifier: Topic :: Software Development :: Libraries :: Application Frameworks
Classifier: Topic :: Software Development :: Libraries :: Python Modules
Classifier: Programming Language :: Python :: Implementation :: MicroPython
Classifier: Programming Language :: Python :: 3
Classifier: License :: Free For Home Use
Classifier: License :: Free for non-commercial use
Classifier: License :: Free To Use But Restricted
Classifier: License :: Other/Proprietary License
Classifier: License :: OSI Approved :: GNU Affero General Public License v3 or later (AGPLv3+)
License-File: LICENSE
